jose_aws_kms_extension/__init__.py
jose_aws_kms_extension/backends/__init__.py
jose_aws_kms_extension/backends/kms/__init__.py
jose_aws_kms_extension/backends/kms/asymmetric/__init__.py
jose_aws_kms_extension/backends/kms/asymmetric/signing.py
jose_aws_kms_extension/backends/kms/constants.py
jose_aws_kms_extension/backends/kms/symmetric/__init__.py
jose_aws_kms_extension/backends/kms/symmetric/encryption.py
jose_aws_kms_extension/backends/kms/utils.py
jose_aws_kms_extension/constants.py
jose_aws_kms_extension/exceptions.py
jose_aws_kms_extension/jwe.py
jose_aws_kms_extension/jwe_tmp.py
jose_aws_kms_extension/jwk.py
python_jose_aws_kms_extension-1.0.1.dist-info/LICENSE
python_jose_aws_kms_extension-1.0.1.dist-info/METADATA
python_jose_aws_kms_extension-1.0.1.dist-info/WHEEL
python_jose_aws_kms_extension-1.0.1.dist-info/RECORD
