Metadata-Version: 2.1
Name: python-jose_aws-kms-extension
Version: 1.0.1
Summary: AWS KMS extension for 'python-jose' library.
License: Apache-2.0
Author: Lynx Tech
Author-email: lynx-tech@amazon.com
Requires-Python: >=3.8,<4
Classifier: License :: OSI Approved :: Apache Software License
Classifier: Programming Language :: Python :: 3
Classifier: Programming Language :: Python :: 3.8
Classifier: Programming Language :: Python :: 3.9
Classifier: Programming Language :: Python :: 3.10
Classifier: Programming Language :: Python :: 3.11
Requires-Dist: boto3-stubs[kms] (>=1.26.155,<2.0.0)
Requires-Dist: boto3[kms] (>=1.26.155,<2.0.0)
Requires-Dist: python-jose[cryptography] (==3.3.0)
